setup.py
gae_pesapal.egg-info/PKG-INFO
gae_pesapal.egg-info/SOURCES.txt
gae_pesapal.egg-info/dependency_links.txt
gae_pesapal.egg-info/top_level.txt
gae_pesapal.egg-info/zip-safe
lib/__init__.py
lib/models.py
test/tests.py