Metadata-Version: 1.0
Name: gae-pesapal
Version: 0.0.1
Summary: Pesapal NDB Model
Home-page: https://github.com/kelonye/gae-pesapal
Author: Mitchel Kelonye
Author-email: kelonyemitchel@gmail.com
License: MIT
Platform: UNKNOWN
